README.rst
setup.py
djhcup_staging/__init__.py
djhcup_staging/admin.py
djhcup_staging/models.py
djhcup_staging/tasks.py
djhcup_staging/urls.py
djhcup_staging/views.py
djhcup_staging.egg-info/PKG-INFO
djhcup_staging.egg-info/SOURCES.txt
djhcup_staging.egg-info/dependency_links.txt
djhcup_staging.egg-info/top_level.txt
djhcup_staging/templates/djhcup_staging_base.html
djhcup_staging/templates/djhcup_staging_batch_detail.html
djhcup_staging/templates/djhcup_staging_batch_inventory.html
djhcup_staging/templates/djhcup_staging_inventory.html
djhcup_staging/templates/djhcup_staging_object_detail.html
djhcup_staging/templates/djhcup_staging_source_detail.html
djhcup_staging/utils/__init__.py
djhcup_staging/utils/defaults.py
djhcup_staging/utils/misc.py