Metadata-Version: 1.1
Name: djhcup-staging
Version: 0.20140415
Summary: Staging module for the Django-HCUP Hachoir (djhcup)
Home-page: UNKNOWN
Author: T.J. Biel
Author-email: tbiel@med.umich.edu
License: MIT
Platform: UNKNOWN
Classifier: Framework :: Django
Classifier: License :: OSI Approved :: MIT License
Classifier: Topic :: Scientific/Engineering
Requires: djhcup_core (>= 0.20140415)
Provides: djhcup_staging
